README.md
setup.py
pulumiverse_dynatrace/__init__.py
pulumiverse_dynatrace/_inputs.py
pulumiverse_dynatrace/_utilities.py
pulumiverse_dynatrace/activegate_token.py
pulumiverse_dynatrace/activegate_updates.py
pulumiverse_dynatrace/ag_token.py
pulumiverse_dynatrace/aix_extension.py
pulumiverse_dynatrace/alerting.py
pulumiverse_dynatrace/alerting_profile.py
pulumiverse_dynatrace/ansible_tower_notification.py
pulumiverse_dynatrace/api_detection.py
pulumiverse_dynatrace/api_token.py
pulumiverse_dynatrace/app_monitoring.py
pulumiverse_dynatrace/application_anomalies.py
pulumiverse_dynatrace/application_data_privacy.py
pulumiverse_dynatrace/application_detection_rule.py
pulumiverse_dynatrace/application_detection_rule_v2.py
pulumiverse_dynatrace/application_error_rules.py
pulumiverse_dynatrace/appsec_notification.py
pulumiverse_dynatrace/attack_alerting.py
pulumiverse_dynatrace/attack_allowlist.py
pulumiverse_dynatrace/attack_rules.py
pulumiverse_dynatrace/attack_settings.py
pulumiverse_dynatrace/attribute_allow_list.py
pulumiverse_dynatrace/attribute_block_list.py
pulumiverse_dynatrace/attribute_masking.py
pulumiverse_dynatrace/attributes_preferences.py
pulumiverse_dynatrace/audit_log.py
pulumiverse_dynatrace/automation_business_calendar.py
pulumiverse_dynatrace/automation_controller_connections.py
pulumiverse_dynatrace/automation_scheduling_rule.py
pulumiverse_dynatrace/automation_workflow.py
pulumiverse_dynatrace/automation_workflow_aws_connections.py
pulumiverse_dynatrace/automation_workflow_jira.py
pulumiverse_dynatrace/automation_workflow_k8s_connections.py
pulumiverse_dynatrace/automation_workflow_slack.py
pulumiverse_dynatrace/autotag.py
pulumiverse_dynatrace/autotag_rules.py
pulumiverse_dynatrace/autotag_v2.py
pulumiverse_dynatrace/aws_anomalies.py
pulumiverse_dynatrace/aws_credentials.py
pulumiverse_dynatrace/aws_service.py
pulumiverse_dynatrace/azure_credentials.py
pulumiverse_dynatrace/azure_service.py
pulumiverse_dynatrace/browser_monitor.py
pulumiverse_dynatrace.egg-info/PKG-INFO
pulumiverse_dynatrace.egg-info/SOURCES.txt
pulumiverse_dynatrace.egg-info/dependency_links.txt
pulumiverse_dynatrace.egg-info/not-zip-safe
pulumiverse_dynatrace.egg-info/requires.txt
pulumiverse_dynatrace.egg-info/top_level.txt
