Metadata-Version: 2.1
Name: pulumiverse-dynatrace
Version: 0.33.0
Summary: A Pulumi package for creating and managing Dynatrace cloud resources.
Home-page: https://www.pulumi.com
License: Apache-2.0
Project-URL: Repository, https://github.com/pulumiverse/pulumi-dynatrace
Keywords: pulumi dynatrace category/infrastructure pulumiverse
Requires-Python: >=3.9
